cloudlabeling/__init__.py
cloudlabeling/cloudlabeling.py
cloudlabeling/server.py
cloudlabeling/data/example.json
cloudlabeling-0.0.16.dist-info/LICENSE
cloudlabeling-0.0.16.dist-info/METADATA
cloudlabeling-0.0.16.dist-info/WHEEL
cloudlabeling-0.0.16.dist-info/top_level.txt
cloudlabeling-0.0.16.dist-info/RECORD
