Metadata-Version: 2.1
Name: cloudlabeling
Version: 0.0.16
Summary: cloudlabeling API
Home-page: https://github.com/SilvioGiancola/cloudlabeling-api
Author: Silvio Giancola
Author-email: silvio.giancola@kaust.edu.sa
License: MIT
Keywords: cloudlabeling,cloud,labeling,object detection,computer vision,image
Platform: UNKNOWN
Classifier: Development Status :: 3 - Alpha
Classifier: Intended Audience :: Developers
Classifier: Topic :: Software Development :: Build Tools
Classifier: License :: OSI Approved :: MIT License
Classifier: Programming Language :: Python :: 3
Classifier: Programming Language :: Python :: 3.4
Classifier: Programming Language :: Python :: 3.5
Classifier: Programming Language :: Python :: 3.6
Classifier: Programming Language :: Python :: 3.7
Classifier: Programming Language :: Python :: 3.8
Classifier: Programming Language :: Python :: 3.9
Requires-Dist: requests
Requires-Dist: tqdm
Requires-Dist: opencv-python
